{
  "fetched_at": "2026-06-25T23:16:14.079049+00:00",
  "header_label": "czwartek, 25 czerwca",
  "assets": [
    {
      "key": "btc",
      "name": "BTC",
      "sub": "Bitcoin",
      "price": "$59 849",
      "price_change_24h": -1.6,
      "opp": 93,
      "opp_30d": [
        64,
        64,
        65,
        62,
        63,
        72,
        89,
        92,
        93,
        95,
        94,
        91,
        91,
        95,
        94,
        89,
        88,
        85,
        80,
        79,
        78,
        81,
        87,
        87,
        81,
        81,
        83,
        84,
        90,
        93
      ],
      "verdict": {
        "decision": "TAK",
        "level": "okazja",
        "word": "OKAZJA",
        "sublabel": "okno otwarte od 3 dni — akumuluj wg planu",
        "opp": 93,
        "fng": 12,
        "headline": "Rynek od kilku dni jest w strachu i BTC pozostaje tani — okno zakupowe jest otwarte już 3 dni. Dla DCA to dobry okres na zakupy zgodnie z planem, bez pośpiechu i bez zwiększania kwot.",
        "signals": [
          {
            "label": "Nastrój rynku",
            "tone": "good",
            "text": "skrajny strach (12/100) — rynek wyprzedany, historycznie sprzyja dokupowaniu"
          },
          {
            "label": "Cena vs 3 mies.",
            "tone": "good",
            "text": "przy dolnej granicy zakresu 3 mies. — kupujesz blisko lokalnego dołka"
          },
          {
            "label": "Trend 30 dni",
            "tone": "good",
            "text": "-21,1% przez miesiąc — kupujesz taniej niż miesiąc temu"
          }
        ],
        "home_signals": [
          {
            "label": "Nastrój",
            "tone": "good",
            "text": "skrajny strach · 12/100"
          },
          {
            "label": "Cena",
            "tone": "good",
            "text": "-21,1%/30d · taniej niż miesiąc temu"
          }
        ]
      },
      "forecast": {
        "horizon_days": 7,
        "score_base": 92,
        "score_range": [
          94,
          100
        ],
        "clamped": "hi",
        "direction": "up",
        "confidence": "medium",
        "total_delta": 9,
        "rules": [
          {
            "name": "Wolumen",
            "delta": 3,
            "note": "Ruch w dół z umiarkowanym wolumenem (+19% vs 30d)"
          },
          {
            "name": "Powrót do średniej",
            "delta": 0,
            "note": "trwały trend spadkowy — reguła odbicia wyciszona (w trendzie myli kierunek)"
          },
          {
            "name": "Momentum",
            "delta": 3,
            "note": "2 dni z rzędu w dół — kontynuacja, rynek tanieje"
          },
          {
            "name": "Cykl",
            "delta": 3,
            "note": "26 mies. po halvingu — cykl po szczycie, okna zakupowe raczej się poprawiają"
          }
        ]
      }
    },
    {
      "key": "bnb",
      "name": "BNB",
      "sub": "Binance Coin",
      "price": "$559",
      "price_change_24h": -0.6,
      "opp": 90,
      "opp_30d": [
        52,
        56,
        53,
        30,
        33,
        41,
        60,
        72,
        78,
        88,
        86,
        79,
        79,
        83,
        85,
        78,
        79,
        76,
        73,
        71,
        72,
        74,
        84,
        84,
        79,
        79,
        80,
        83,
        88,
        90
      ],
      "verdict": {
        "decision": "TAK",
        "level": "okazja",
        "word": "OKAZJA",
        "sublabel": "dobry moment na zakup — rynek w strachu",
        "opp": 90,
        "fng": 12,
        "headline": "Rynek jest w strachu, a BNB jest tańszy niż miesiąc temu — dla strategii stałych zakupów (DCA) to statystycznie lepszy dzień niż zwykle.",
        "signals": [
          {
            "label": "Nastrój rynku",
            "tone": "good",
            "text": "skrajny strach (12/100) — rynek wyprzedany, historycznie sprzyja dokupowaniu"
          },
          {
            "label": "Cena vs 3 mies.",
            "tone": "good",
            "text": "przy dolnej granicy zakresu 3 mies. — kupujesz blisko lokalnego dołka"
          },
          {
            "label": "Trend 30 dni",
            "tone": "good",
            "text": "-14,7% przez miesiąc — kupujesz taniej niż miesiąc temu"
          }
        ],
        "home_signals": [
          {
            "label": "Nastrój",
            "tone": "good",
            "text": "skrajny strach · 12/100"
          },
          {
            "label": "Cena",
            "tone": "good",
            "text": "-14,7%/30d · taniej niż miesiąc temu"
          }
        ]
      },
      "forecast": {
        "horizon_days": 7,
        "score_base": 89,
        "score_range": [
          88,
          100
        ],
        "clamped": null,
        "direction": "up",
        "confidence": "medium",
        "total_delta": 5,
        "rules": [
          {
            "name": "Wolumen",
            "delta": 2,
            "note": "Ruch w dół bez wolumenu (-17% vs 30d) — słabe potwierdzenie"
          },
          {
            "name": "Powrót do średniej",
            "delta": 0,
            "note": "trwały trend spadkowy — reguła odbicia wyciszona (w trendzie myli kierunek)"
          },
          {
            "name": "Momentum",
            "delta": 3,
            "note": "2 dni z rzędu w dół — kontynuacja, rynek tanieje"
          },
          {
            "name": "Siła BNB vs BTC",
            "delta": 0,
            "note": "BNB względem Bitcoina +1,7% w 7d — porusza się z rynkiem"
          }
        ]
      }
    }
  ]
}